validate_call_safe-0.3.5.dist-info/METADATA
validate_call_safe-0.3.5.dist-info/WHEEL
validate_call_safe/__init__.py
validate_call_safe/decorator.py
validate_call_safe/errors/__init__.py
validate_call_safe/errors/details.py
validate_call_safe/errors/model.py
validate_call_safe-0.3.5.dist-info/RECORD
