Metadata-Version: 2.1
Name: validate-call-safe
Version: 0.3.5
Summary: Safe, non-error-raising, alternative to Pydantic validate_call decorator
Author-Email: Louis Maddox <louismmx@gmail.com>
License: MIT
Project-URL: Homepage, https://github.com/lmmx/validate-call-safe
Project-URL: Repository, https://github.com/lmmx/validate-call-safe.git
Requires-Python: >=3.10
Requires-Dist: pydantic>=2.0.1
Requires-Dist: typing-extensions>=4.12.2
